epaper/__init__.py
epaper/e-Paper/RaspberryPi_JetsonNano/__init__.py
epaper/e-Paper/RaspberryPi_JetsonNano/python/__init__.py
epaper/e-Paper/RaspberryPi_JetsonNano/python/lib/__init__.py
epaper/e-Paper/RaspberryPi_JetsonNano/python/lib/waveshare_epd/DEV_Config_32.so
epaper/e-Paper/RaspberryPi_JetsonNano/python/lib/waveshare_epd/DEV_Config_64.so
epaper/e-Paper/RaspberryPi_JetsonNano/python/lib/waveshare_epd/__init__.py
epaper/e-Paper/RaspberryPi_JetsonNano/python/lib/waveshare_epd/epd13in3b.py
epaper/e-Paper/RaspberryPi_JetsonNano/python/lib/waveshare_epd/epd13in3k.py
epaper/e-Paper/RaspberryPi_JetsonNano/python/lib/waveshare_epd/epd1in02.py
epaper/e-Paper/RaspberryPi_JetsonNano/python/lib/waveshare_epd/epd1in54.py
epaper/e-Paper/RaspberryPi_JetsonNano/python/lib/waveshare_epd/epd1in54_V2.py
epaper/e-Paper/RaspberryPi_JetsonNano/python/lib/waveshare_epd/epd1in54b.py
epaper/e-Paper/RaspberryPi_JetsonNano/python/lib/waveshare_epd/epd1in54b_V2.py
epaper/e-Paper/RaspberryPi_JetsonNano/python/lib/waveshare_epd/epd1in54c.py
epaper/e-Paper/RaspberryPi_JetsonNano/python/lib/waveshare_epd/epd1in64g.py
epaper/e-Paper/RaspberryPi_JetsonNano/python/lib/waveshare_epd/epd2in13.py
epaper/e-Paper/RaspberryPi_JetsonNano/python/lib/waveshare_epd/epd2in13_V2.py
epaper/e-Paper/RaspberryPi_JetsonNano/python/lib/waveshare_epd/epd2in13_V3.py
epaper/e-Paper/RaspberryPi_JetsonNano/python/lib/waveshare_epd/epd2in13_V4.py
epaper/e-Paper/RaspberryPi_JetsonNano/python/lib/waveshare_epd/epd2in13b_V3.py
epaper/e-Paper/RaspberryPi_JetsonNano/python/lib/waveshare_epd/epd2in13b_V4.py
epaper/e-Paper/RaspberryPi_JetsonNano/python/lib/waveshare_epd/epd2in13bc.py
epaper/e-Paper/RaspberryPi_JetsonNano/python/lib/waveshare_epd/epd2in13d.py
epaper/e-Paper/RaspberryPi_JetsonNano/python/lib/waveshare_epd/epd2in13g.py
epaper/e-Paper/RaspberryPi_JetsonNano/python/lib/waveshare_epd/epd2in36g.py
epaper/e-Paper/RaspberryPi_JetsonNano/python/lib/waveshare_epd/epd2in66.py
waveshare_epaper-1.3.0.dist-info/LICENSE
waveshare_epaper-1.3.0.dist-info/METADATA
waveshare_epaper-1.3.0.dist-info/WHEEL
waveshare_epaper-1.3.0.dist-info/RECORD
