Metadata-Version: 2.1
Name: waveshare-epaper
Version: 1.3.0
Summary: Waveshare e-paper package for Python on Raspberry Pi
Home-page: https://github.com/yskoht/waveshare-epaper
License: MIT
Author: yskoht
Author-email: ysk.oht@gmail.com
Classifier: License :: OSI Approved :: MIT License
Classifier: Programming Language :: Python :: 2
Classifier: Programming Language :: Python :: 2.7
Classifier: Programming Language :: Python :: 3
Classifier: Programming Language :: Python :: 3.4
Classifier: Programming Language :: Python :: 3.5
Classifier: Programming Language :: Python :: 3.6
Classifier: Programming Language :: Python :: 3.7
Classifier: Programming Language :: Python :: 3.8
Classifier: Programming Language :: Python :: 3.9
Classifier: Programming Language :: Python :: 3.10
Classifier: Programming Language :: Python :: 3.11
Classifier: Topic :: Software Development :: Libraries :: Python Modules
Requires-Dist: RPi.GPIO (>=0.7.0,<0.8.0)
Requires-Dist: spidev (>=3.5,<4.0)
Project-URL: Repository, https://github.com/yskoht/waveshare-epaper
